abdullah_graph_eq/__init__.py
abdullah_graph_eq/grapher.py
abdullah_graph_eq/parser.py
abdullah_graph_eq-0.1.0.dist-info/licenses/LICENSE
tests/__init__.py
tests/test_grapher.py
tests/test_parser.py
abdullah_graph_eq-0.1.0.dist-info/METADATA
abdullah_graph_eq-0.1.0.dist-info/WHEEL
abdullah_graph_eq-0.1.0.dist-info/top_level.txt
abdullah_graph_eq-0.1.0.dist-info/RECORD
