Metadata-Version: 2.4
Name: abdullah_graph_eq
Version: 0.1.0
Summary: A Python package for graphing mathematical equations from string input
Home-page: https://github.com/abdullahmashhadi/abdullah_graph_eq
Author: abdullahmashhadi
Author-email: Abdullah <your.email@example.com>
License: MIT
Project-URL: Homepage, https://github.com/yourusername/abdullah_graph_eq
Project-URL: Bug Reports, https://github.com/yourusername/abdullah_graph_eq/issues
Project-URL: Source, https://github.com/yourusername/abdullah_graph_eq
Keywords: mathematics,plotting,graphing,equations,visualization
Classifier: Development Status :: 3 - Alpha
Classifier: Intended Audience :: Developers
Classifier: Intended Audience :: Education
Classifier: License :: OSI Approved :: MIT License
Classifier: Operating System :: OS Independent
Classifier: Programming Language :: Python :: 3
Classifier: Programming Language :: Python :: 3.7
Classifier: Programming Language :: Python :: 3.8
Classifier: Programming Language :: Python :: 3.9
Classifier: Programming Language :: Python :: 3.10
Classifier: Programming Language :: Python :: 3.11
Classifier: Topic :: Scientific/Engineering :: Mathematics
Classifier: Topic :: Scientific/Engineering :: Visualization
Requires-Python: >=3.7
License-File: LICENSE
Requires-Dist: matplotlib>=3.5.0
Requires-Dist: numpy>=1.20.0
Requires-Dist: sympy>=1.9.0
Dynamic: author
Dynamic: home-page
Dynamic: license-file
Dynamic: requires-python
